MANIFEST.in
README.md
setup.py
ska
ska_kmers.c
ska_kmers.pyx
fast_ska.egg-info/PKG-INFO
fast_ska.egg-info/SOURCES.txt
fast_ska.egg-info/dependency_links.txt
fast_ska.egg-info/requires.txt
fast_ska.egg-info/top_level.txt