Metadata-Version: 1.1
Name: fast-ska
Version: 0.9.3
Summary: A fast Cython implementation of the "Streaming K-mer Assignment" algorithm initially described in Lambert et al. 2014 (PMID: 24837674)
Home-page: https://github.com/marvin-jens/fast_ska
Author: Marvin Jens
Author-email: mjens@mit.edu
License: MIT
Keywords: rna rbns k-mer kmer statistics biology bioinformatics
Platform: UNKNOWN
Classifier: Development Status :: 4 - Beta
Classifier: Intended Audience :: Developers
Classifier: Intended Audience :: Science/Research
Classifier: License :: OSI Approved :: MIT License
Classifier: Programming Language :: Python :: 2
Classifier: Programming Language :: Python :: 2.6
Classifier: Programming Language :: Python :: 2.7
Classifier: Topic :: Scientific/Engineering :: Bio-Informatics
